open_marquesote/__init__.py
open_marquesote/__main__.py
open_marquesote/images/arrow-000.png
open_marquesote/images/arrow-180.png
open_marquesote/images/arrow-circle-315.png
open_marquesote/images/back.png
open_marquesote/images/cross.png
open_marquesote/images/home.png
open_marquesote/images/ma-icon-128.png
open_marquesote/images/ma-icon-256.png
open_marquesote/images/ma-icon-64.png
open_marquesote/images/next.png
open_marquesote/images/printer.png
open_marquesote/images/reload.png
open_marquesote/images/ui-tab--plus.png
open_marquesote-1.0.1.dist-info/LICENSE
open_marquesote-1.0.1.dist-info/METADATA
open_marquesote-1.0.1.dist-info/WHEEL
open_marquesote-1.0.1.dist-info/top_level.txt
open_marquesote-1.0.1.dist-info/RECORD
