Metadata-Version: 2.1
Name: open-marquesote
Version: 1.0.1
Summary: Minimal Web Browser
Home-page: UNKNOWN
Author: William José Moreno Reyes
Author-email: williamjmorenor@gmail.com
License: UNKNOWN
Platform: UNKNOWN
Classifier: Development Status :: 5 - Production/Stable
Requires-Dist: PyQtWebEngine
Requires-Dist: waitress
